{
  "ACH01": {
    "earned": true,
    "earned_time": 1719172625
  },
  "ACH02": {
    "earned": false,
    "earned_time": 0
  },
  "ACH03": {
    "earned": false,
    "earned_time": 0
  },
  "ACH04": {
    "earned": false,
    "earned_time": 0
  },
  "ACH05": {
    "earned": false,
    "earned_time": 0
  },
  "ACH06": {
    "earned": false,
    "earned_time": 0
  },
  "ACH07": {
    "earned": false,
    "earned_time": 0
  },
  "ACH08": {
    "earned": false,
    "earned_time": 0
  },
  "ACH09": {
    "earned": false,
    "earned_time": 0
  },
  "ACH10": {
    "earned": false,
    "earned_time": 0
  },
  "ACH11": {
    "earned": false,
    "earned_time": 0
  },
  "ACH12": {
    "earned": false,
    "earned_time": 0
  },
  "ACH13": {
    "earned": false,
    "earned_time": 0
  },
  "ACH14": {
    "earned": false,
    "earned_time": 0
  },
  "ACH15": {
    "earned": false,
    "earned_time": 0
  },
  "ACH16": {
    "earned": false,
    "earned_time": 0
  },
  "ACH17": {
    "earned": false,
    "earned_time": 0
  },
  "ACH18": {
    "earned": false,
    "earned_time": 0
  },
  "ACH19": {
    "earned": false,
    "earned_time": 0
  },
  "ACH20": {
    "earned": false,
    "earned_time": 0
  },
  "ACH21": {
    "earned": false,
    "earned_time": 0
  },
  "ACH22": {
    "earned": false,
    "earned_time": 0
  },
  "ACH23": {
    "earned": false,
    "earned_time": 0
  },
  "ACH24": {
    "earned": false,
    "earned_time": 0
  },
  "ACH25": {
    "earned": false,
    "earned_time": 0
  },
  "ACH26": {
    "earned": false,
    "earned_time": 0
  },
  "ACH27": {
    "earned": false,
    "earned_time": 0
  },
  "ACH28": {
    "earned": false,
    "earned_time": 0
  },
  "ACH29": {
    "earned": false,
    "earned_time": 0
  },
  "ACH30": {
    "earned": false,
    "earned_time": 0
  },
  "ACH31": {
    "earned": false,
    "earned_time": 0
  },
  "ACH32": {
    "earned": false,
    "earned_time": 0
  },
  "ACH33": {
    "earned": false,
    "earned_time": 0
  },
  "ACH34": {
    "earned": false,
    "earned_time": 0
  },
  "ACH35": {
    "earned": false,
    "earned_time": 0
  },
  "ACH36": {
    "earned": false,
    "earned_time": 0
  },
  "ACH37": {
    "earned": false,
    "earned_time": 0
  },
  "ACH38": {
    "earned": false,
    "earned_time": 0
  },
  "ACH39": {
    "earned": false,
    "earned_time": 0
  },
  "ACH40": {
    "earned": false,
    "earned_time": 0
  },
  "ACH41": {
    "earned": false,
    "earned_time": 0
  },
  "ACH42": {
    "earned": false,
    "earned_time": 0
  },
  "ACH43": {
    "earned": false,
    "earned_time": 0
  },
  "ACH44": {
    "earned": false,
    "earned_time": 0
  },
  "ACH45": {
    "earned": false,
    "earned_time": 0
  },
  "ACH46": {
    "earned": false,
    "earned_time": 0
  },
  "ACH47": {
    "earned": false,
    "earned_time": 0
  },
  "ACH48": {
    "earned": false,
    "earned_time": 0
  },
  "ACH49": {
    "earned": false,
    "earned_time": 0
  },
  "ACH50": {
    "earned": false,
    "earned_time": 0
  },
  "ACH51": {
    "earned": false,
    "earned_time": 0
  },
  "ACH52": {
    "earned": false,
    "earned_time": 0
  },
  "ACH53": {
    "earned": false,
    "earned_time": 0
  },
  "ACH54": {
    "earned": false,
    "earned_time": 0
  },
  "ACH55": {
    "earned": false,
    "earned_time": 0
  },
  "ACH56": {
    "earned": false,
    "earned_time": 0
  },
  "ACH57": {
    "earned": false,
    "earned_time": 0
  },
  "ACH58": {
    "earned": false,
    "earned_time": 0
  },
  "ACH59": {
    "earned": false,
    "earned_time": 0
  },
  "ACH60": {
    "earned": false,
    "earned_time": 0
  },
  "ACH61": {
    "earned": false,
    "earned_time": 0
  },
  "ACH62": {
    "earned": false,
    "earned_time": 0
  },
  "ACH63": {
    "earned": false,
    "earned_time": 0
  },
  "ACH64": {
    "earned": false,
    "earned_time": 0
  },
  "ACH65": {
    "earned": false,
    "earned_time": 0
  },
  "ACH66": {
    "earned": false,
    "earned_time": 0
  },
  "ACH67": {
    "earned": false,
    "earned_time": 0
  },
  "ACH68": {
    "earned": false,
    "earned_time": 0
  },
  "ACH69": {
    "earned": false,
    "earned_time": 0
  },
  "ACH70": {
    "earned": false,
    "earned_time": 0
  }
}